zerossl/__init__.py
zerossl/main.py
zerossl/openssl.py
zerossl/route53.py
zerossl/zerossl.py
zerossl-0.1.3.dist-info/LICENSE
zerossl-0.1.3.dist-info/METADATA
zerossl-0.1.3.dist-info/WHEEL
zerossl-0.1.3.dist-info/entry_points.txt
zerossl-0.1.3.dist-info/top_level.txt
zerossl-0.1.3.dist-info/RECORD
