Metadata-Version: 2.1
Name: zerossl
Version: 0.1.3
Summary: Interact with ZeroSSL API
Home-page: https://github.com/yadhu621/zerossl
Author: Yadhu
Author-email: yadhu621@gmail.com
License: MIT
Keywords: zerossl
Platform: UNKNOWN
Classifier: Programming Language :: Python :: 3
Classifier: License :: OSI Approved :: MIT License
Classifier: Operating System :: OS Independent
Requires-Dist: requests (==2.26.0)
Requires-Dist: pyOpenSSL (==22.0.0)
Requires-Dist: boto3 (==1.23.0)
